MANIFEST.in
setup.py
sf_uploader.egg-info/PKG-INFO
sf_uploader.egg-info/SOURCES.txt
sf_uploader.egg-info/dependency_links.txt
sf_uploader.egg-info/entry_points.txt
sf_uploader.egg-info/namespace_packages.txt
sf_uploader.egg-info/not-zip-safe
sf_uploader.egg-info/requires.txt
sf_uploader.egg-info/top_level.txt
sfext/__init__.py
sfext/uploader/__init__.py
sfext/uploader/uploader.py
sfext/uploader/db/__init__.py
sfext/uploader/db/asset.py
sfext/uploader/processors/__init__.py
sfext/uploader/processors/imageresize.py
sfext/uploader/scripts/__init__.py
sfext/uploader/scripts/reprocess.py
sfext/uploader/static/css/fileuploader.css
sfext/uploader/static/img/loading.gif
sfext/uploader/static/js/fileuploader.js
sfext/uploader/stores/__init__.py
sfext/uploader/stores/fsstore.py
sfext/uploader/tests/__init__.py
sfext/uploader/tests/conftest.py
sfext/uploader/tests/test_basics.py
sfext/uploader/tests/test_converters.py
sfext/uploader/tests/test_db.py
sfext/uploader/tests/test_fsstore.py