Metadata-Version: 1.1
Name: sf-uploader
Version: 1.0.3
Summary: Upload module for starflyer
Home-page: UNKNOWN
Author: Christian Scholz
Author-email: cs@comlounge.net
License: BSD
Platform: any
Classifier: Environment :: Web Environment
Classifier: Intended Audience :: Developers
Classifier: License :: OSI Approved :: BSD License
Classifier: Operating System :: OS Independent
Classifier: Programming Language :: Python
Classifier: Topic :: Internet :: WWW/HTTP :: Dynamic Content
Classifier: Topic :: Software Development :: Libraries :: Python Modules
